napari_labeling/__init__.py
napari_labeling/_create_widget.py
napari_labeling/_reader.py
napari_labeling/_version.py
napari_labeling/_widget.py
napari_labeling/_writer.py
napari_labeling/napari.yaml
napari_labeling/_tests/__init__.py
napari_labeling/_tests/test_reader.py
napari_labeling/_tests/test_widget.py
napari_labeling/_tests/test_writer.py
napari_labeling-0.1.2.dist-info/LICENSE
napari_labeling-0.1.2.dist-info/METADATA
napari_labeling-0.1.2.dist-info/WHEEL
napari_labeling-0.1.2.dist-info/entry_points.txt
napari_labeling-0.1.2.dist-info/top_level.txt
napari_labeling-0.1.2.dist-info/RECORD
